Workbook

Sheet Dashboard
B2: Wedding & Engagement Plan
B3: All figures in Rp million. Blue = an input you can change · Black = formula · Green = pulled from another tab.
B5: Where the money stands
B6: Current joint balance (Blugether) | C6: =Assumptions!C5
B7: Combined saving / month | C7: =Assumptions!C8
B8: Engagement phase cost (event + ring) | C8: =Engagement!C14
B9: Wedding total — Option A | C9: ='Wedding Budget'!C40
B10: Wedding total — Option B | C10: ='Wedding Budget'!D40
B13: Can we afford it, and when?
B14: Milestone | C14: Funds available | D14: Verdict
B15: Engagement — Nov 2026 | C15: =Cashflow!C7+Cashflow!D7 | D15: =IF(C15>=Engagement!C14,"Funded ✓","Short")
B16: Wedding Option A — Aug 2027 | C16: =Cashflow!F16 | D16: =IF(C16>='Wedding Budget'!C40,"Funded ✓, surplus "&TEXT(C16-'Wedding Budget'!C40,"#,##0.0"),"Short by "&TEXT('Wedding Budget'!C40-C16,"#,##0.0"))
B17: Wedding Option A — Nov 2027 | C17: =Cashflow!F19 | D17: =IF(C17>='Wedding Budget'!C40,"Funded ✓, surplus "&TEXT(C17-'Wedding Budget'!C40,"#,##0.0"),"Short by "&TEXT('Wedding Budget'!C40-C17,"#,##0.0"))
B18: Wedding Option B — Dec 2027 | C18: =Cashflow!F20 | D18: =IF(C18>='Wedding Budget'!D40,"Funded ✓","Short by "&TEXT('Wedding Budget'!D40-C18,"#,##0.0")&" mio")
B20: Read the tabs left → right: Assumptions · Engagement · Wedding Budget (A vs B) · Cashflow · Timeline.

Sheet Assumptions
B2: Assumptions & Levers
B3: Change any blue cell — every other tab recalculates.
B4: Item | C4: Value | D4: Note
B5: Current joint balance | C5: 50 | D5: Blugether joint savings today (Sep 2026)
B6: Girl — contribution / month | C6: 2 | D6: Monthly transfer into Blugether
B7: Boy — contribution / month | C7: 3 | D7: Monthly transfer into Blugether
B8: Combined saving / month | C8: =C6+C7 | D8: Auto: girl + boy
B9: Engagement ring (for the girl) | C9: 12.8 | D9: One-off, paid around engagement
B10: Wedding rings (both) | C10: 9 | D10: One-off, inside the wedding budget
B11: Groom loafers — already bought | C11: 1.6 | D11: Sunk cost — already paid, not from the pool
B12: Contingency / buffer | C12: 0.1 | D12: % added on top of the wedding line items
B15: Timeline anchors
B16: Anchor | C16: When | D16: Detail
B17: Plan start | C17: Sep 2026 | D17: Today
B18: Engagement | C18: Nov 2026 | D18: At the girl's home, ~20 people
B19: Wedding window | C19: 2027 | D19: Subtle wedding — see Timeline tab for dates

Sheet Engagement
B2: Engagement — Nov 2026
B3: At the girl's home · home-cooked meal · ~20 guests · target Rp 5.0 mio (the ring is tracked separately).
B5: Item | C5: Cost | D5: Detail
B6: Tenda + chairs (rental) | C6: 1.5 | D6: Small tent, 20 chairs, tables — 1 day
B7: Decoration & flowers | C7: 1.5 | D7: Backdrop, drapes, fresh flowers, lighting
B8: Food top-up & drinks | C8: 1 | D8: Ingredients for the home-cooked spread, snacks, ice, water
B9: Seserahan / hantaran trays | C9: 0.5 | D9: Trays + wrapping for the exchange gifts
B10: Documentation | C10: 0.3 | D10: Half-day photographer, or a skilled friend
B11: Buffer / misc | C11: 0.2 | D11: Small unexpected extras
B12: Engagement event total | C12: =SUM(C6:C11) | D12: Target was Rp 5.0 mio
B13: vs target (5.0) | C13: =5-C12 | D13: Positive = under target
B14: Engagement PHASE total (event + ring) | C14: =C12+Assumptions!C9 | D14: ="Ring Rp "&TEXT(Assumptions!C9,"#,##0.0")&" mio added"

Sheet Wedding Budget
B2: Wedding Budget — Option A vs Option B
B3: Subtle Javanese-adat wedding at Rooang. Pre-wed kept to the siraman; full reception day (MC, music, hotel). A = intimate/lean · B = grander. Rp mio.
B5: Key drivers | C5: Option A | D5: Option B | E5: Note
B6: Guest count (reception) | C6: 50 | D6: 100 | E6: Subtle = small. Drives catering & souvenirs
B7: Catering rate / guest | C7: 0.15 | D7: 0.2 | E7: Per head — Dharmawangsa-area boutique
B8: Souvenir rate / guest | C8: 0.015 | D8: 0.025 | E8: Per favour
B10: Line item | C10: Option A | D10: Option B | E10: What it covers
B11: Siraman ceremony | C11: 3 | D11: 5 | E11: Setaman flowers, seven-spring water, kendi, dawet, tumpeng, simple gendhing
B12: Siraman family catering | C12: 1.5 | D12: 3 | E12: Home meal for family on the siraman day
B13: Venue — Rooang Dharmawangsa | C13: 15 | D13: 25 | E13: A: reception (akad at home) · B: full akad + reception
B14: Panggih (temu manten) props | C14: 2 | D14: 3.5 | E14: Kembar mayang ×2, suruh, egg, kacar-kucur, sindur
B15: Penghulu / KUA (akad) | C15: 0.6 | D15: 0.6 | E15: Officiant outside office hours
B16: Day-of coordinator (akad + reception) | C16: 3 | D16: 5 | E16: Koordinator hari-H — runs the rundown, cues vendors
B17: MC / host (akad + reception) | C17: 2.5 | D17: 4 | E17: Bilingual host keeping the flow
B18: Reception catering | C18: =C6*C7 | D18: =D6*D7 | E18: Guests × rate / guest
B19: Reception decor & floral — Rooang | C19: 5 | D19: 12 | E19: Subtle & elegant: stage, entrance, aisle, table florals
B20: Entertainment — live music | C20: 3.5 | D20: 8 | E20: A: acoustic trio · B: full band
B21: Hotel room — bridal suite (1 night) | C21: 2.5 | D21: 5 | E21: Wedding-night room for the couple
B22: Wedding cake & dessert | C22: 1 | D22: 2.5 | E22: Cake + sweet corner
B23: Souvenirs / favours | C23: =C6*C8 | D23: =D6*D8 | E23: Guests × rate / guest
B24: Photo & video (2-day) | C24: 6 | D24: 12 | E24: Siraman day + wedding day
B25: Wedding rings (both) | C25: =Assumptions!C10 | D25: =Assumptions!C10 | E25: Linked from Assumptions
B26: Bride — paes MUA + adat busana | C26: 10 | D26: 18 | E26: Paes ageng across siraman, akad, reception
B27: Groom — adat busana | C27: 4 | D27: 6 | E27: Wedding day: beskap, blangkon, keris. Engagement: light grey double-breasted suit. Loafers already bought
B28: Family adat attire | C28: 2 | D28: 4 | E28: Coordinated kebaya/beskap for the parents
B29: Invitations | C29: 0.3 | D29: 1.5 | E29: A: digital · B: digital + printed
B30: Mahar (dowry) | C30: 1 | D30: 3 | E30: Symbolic — set to your intention
B31: Transport & misc | C31: 2 | D31: 3.5 | E31: Two-day logistics, cars, tips
B32: Subtotal | C32: =SUM(C11:C31) | D32: =SUM(D11:D31) | E32: Sum of the line items above
B33: Contingency | C33: =C32*Assumptions!C12 | D33: =D32*Assumptions!C12 | E33: ="Buffer @ "&TEXT(Assumptions!C12,"0%")
B40: WEDDING GRAND TOTAL | C40: =C32+C33 | D40: =D32+D33 | E40: Subtotal + contingency — the number to fund
B41: Option B minus Option A | C41: =D40-C40 | D41: extra for B

Sheet Cashflow
B2: Cashflow projection
B3: Opening + saving − planned outflow = closing. The engagement outflow lands in Nov 2026. All Rp mio.
B4: Month | C4: Opening | D4: Saving | E4: Engagement out | F4: Closing | G4: Milestone
B5: Sep 2026 | C5: =Assumptions!C5 | D5: =Assumptions!C8 | E5: 0 | F5: =C5+D5-E5
B6: Oct 2026 | C6: =F5 | D6: =Assumptions!C8 | E6: 0 | F6: =C6+D6-E6
B7: Nov 2026 | C7: =F6 | D7: =Assumptions!C8 | E7: =Engagement!C14 | F7: =C7+D7-E7 | G7: Engagement + ring
B8: Dec 2026 | C8: =F7 | D8: =Assumptions!C8 | E8: 0 | F8: =C8+D8-E8
B9: Jan 2027 | C9: =F8 | D9: =Assumptions!C8 | E9: 0 | F9: =C9+D9-E9
B10: Feb 2027 | C10: =F9 | D10: =Assumptions!C8 | E10: 0 | F10: =C10+D10-E10
B11: Mar 2027 | C11: =F10 | D11: =Assumptions!C8 | E11: 0 | F11: =C11+D11-E11
B12: Apr 2027 | C12: =F11 | D12: =Assumptions!C8 | E12: 0 | F12: =C12+D12-E12
B13: May 2027 | C13: =F12 | D13: =Assumptions!C8 | E13: 0 | F13: =C13+D13-E13
B14: Jun 2027 | C14: =F13 | D14: =Assumptions!C8 | E14: 0 | F14: =C14+D14-E14 | G14: ← Option A window
B15: Jul 2027 | C15: =F14 | D15: =Assumptions!C8 | E15: 0 | F15: =C15+D15-E15
B16: Aug 2027 | C16: =F15 | D16: =Assumptions!C8 | E16: 0 | F16: =C16+D16-E16
B17: Sep 2027 | C17: =F16 | D17: =Assumptions!C8 | E17: 0 | F17: =C17+D17-E17 | G17: ← Option A window
B18: Oct 2027 | C18: =F17 | D18: =Assumptions!C8 | E18: 0 | F18: =C18+D18-E18
B19: Nov 2027 | C19: =F18 | D19: =Assumptions!C8 | E19: 0 | F19: =C19+D19-E19
B20: Dec 2027 | C20: =F19 | D20: =Assumptions!C8 | E20: 0 | F20: =C20+D20-E20 | G20: ← Option B window
B22: Note | C22: Closing balance = money you could put on the wedding that month. Compare it to the Wedding Budget grand totals.

Sheet Timeline
B2: Timeline scenarios
B3: Same savings plan, three wedding dates. 'Funds available' is that month's closing balance from Cashflow.
B5: Scenario | C5: Wedding | D5: Funds avail. | E5: Option A gap | F5: Option B gap | G5: Read
B6: 1 · Intimate & earliest | C6: Aug 2027 | D6: =Cashflow!F16 | E6: =D6-'Wedding Budget'!C40 | F6: =D6-'Wedding Budget'!D40 | G6: =IF(E6>=0,IF(F6>=0,"Both A & B funded ✓","Option A funded; B short"),"A short — add gifts/angpau or more months")
B7: 2 · Comfortable cushion | C7: Nov 2027 | D7: =Cashflow!F19 | E7: =D7-'Wedding Budget'!C40 | F7: =D7-'Wedding Budget'!D40 | G7: =IF(E7>=0,IF(F7>=0,"Both A & B funded ✓","Option A funded; B short"),"A short — add gifts/angpau or more months")
B8: 3 · Full grandeur (Opt B) | C8: Dec 2027 | D8: =Cashflow!F20 | E8: =D8-'Wedding Budget'!C40 | F8: =D8-'Wedding Budget'!D40 | G8: =IF(E8>=0,IF(F8>=0,"Both A & B funded ✓","Option A funded; B short"),"A short — add gifts/angpau or more months")
B11: Gap = funds available − wedding grand total. Positive = surplus, negative = shortfall.
B12: Upside not modelled: angpau/gift money at the reception often offsets 30–50% of catering. Treat it as a cushion, not a plan.
B13: Recommendation
B14: Option A — siraman + a full reception day at an intimate scale — clears around August 2027 and sits on a cushion by Oct–Nov. Option B (grander, ~100 guests) is a 2028 project, or needs a bigger monthly saving plus angpau.
